{
  "conditions": [
    {
      "type": "forge:and",
      "values": [
        {
          "type": "appliedenergistics2:part_exists",
          "part": "part.storage_monitor"
        },
        {
          "type": "appliedenergistics2:material_exists",
          "part": "material.engineering_processor"
        }
      ]
    }
  ],
  "result": {
    "type": "appliedenergistics2:part",
    "part": "part.ThroughputMonitor"
  },
  "type": "appliedenergistics2:part_shapeless",
  "ingredients": [
    {
      "type": "appliedenergistics2:part",
      "part": "part.level_emitter"
    },
    {
      "type": "forge:ore_dict",
      "ore": "itemIlluminatedPanel"
    }
  ]
}
